{
  "id_and_class": {
    "theory_title": "复合理论",
    "summary": "这一归入二元论的理论一般主张，人是一个由两个不同却又亲密统一的要素构成的复合实体，通常是一个非物质的灵魂／形式与一个物质的身体。它力图避免笛卡尔式二元论的根本分离，同时维持意识的不可还原性，主张灵魂充当身体的实体形式。",
    "associated_thinkers": [],
    "category": "二元论",
    "subcategory": "复合二元论",
    "core_identity_tagline": "作为统一之灵魂／身体复合体的意识",
    "classification_tags": [
      "dualism",
      "composite",
      "hylomorphism",
      "immaterial"
    ]
  },
  "conceptual_ground": {
    "explanatory_identity_claim": "意识被认定为复合实体（有灵魂的身体）的活动或功能，产生于在物质组成部分中得以实现的非物质形式（灵魂）。（根据其归入二元论、以及在来源中与托马斯主义二元论相邻近而推断）",
    "ontological_status": "二元论（复合／质形论）",
    "mind_body_relationship": "心灵（灵魂）是身体的实体形式，构成一个统一的复合体。这种关系是亲密的、非笛卡尔式的，其中形式是使活的身体成其所是所必需的。",
    "primitive_or_emergent_status": "原初的（灵魂／形式对于人这一有意识实体的构成而言是根本的。）",
    "emergence_type": "该理论聚焦于复合实体的结构统一，而非物理主义还原意义上的涌现。非物质的形式是一种不可还原的组织原理。",
    "subjectivity_and_intentionality": "主体性存在于灵魂／形式不可还原的第一人称本性之中，后者不可分地统一，使确定的、意向性的思想内容成为可能。",
    "qualia_account": "感受质被说明为源自统一的灵魂—身体复合体之活动的质性特征，无法还原为纯粹量化的物理描述。",
    "ontological_commitments": "非物质的灵魂／形式；物质的身体；一个单一、统一的复合实体（人）。",
    "epistemic_access": "既可通过对物理身体过程的第三人称观察通达，也需通过对心理活动／形式的第一人称内省通达。",
    "constituents_and_structure": "一个单一、统一的实体（人），由两种根本不同却又相整合的原理构成：一个非物质／构型的灵魂（形式）与物质组成部分（身体）。"
  },
  "mechanism_and_dynamics": {
    "scope_of_consciousness": "现象性、自我觉知、能动性（作为统一复合实体的活动）。",
    "distinctive_mechanism_or_principle": "灵魂／形式充当组织原理（形式），使物质身体的能力得以现实化，从而产生有意识的活动［由 7.5 节相关概念推断］。",
    "dynamics_of_emergence": "意识被理解为有灵魂之复合体的一种动态活动，而非一种静态属性。",
    "location_and_distribution": "定域于统一的活的身体或有机体。",
    "causation_and_functional_role": "心理活动／灵魂赋予身体形式并使之活动，提供对能动性与统一认知功能所必需的自上而下的因果影响。",
    "integration_or_binding": "心灵／灵魂本然地提供意识的统一，因为它充当整个身体／人的实体形式。",
    "information_flow_or_representation": "隐含地涉及，因为心理活动需要表征，但复合结构从根本上保证了不可分的意识统一。",
    "evolutionary_account": "从所提供的来源尚不清晰；一般而言，纳入一个不可还原的非物质组成部分意味着灵魂／形式并非纯粹是标准达尔文机制的产物。",
    "core_claims_and_evidence": [
      "意识的统一无法仅凭物理大脑各部分的聚合来解释。",
      "灵魂（形式）赋予物理身体以形式，使人成为一个统一的、实体性的实在。",
      "概念性证据在于驳斥还原论唯物主义在说明思想的质性本性方面的充分性。"
    ],
    "basis_of_belief_or_evidence_type": "哲学的、形而上学的"
  },
  "empirics_and_critiques": {
    "testability_status": "概念上可检验（通过哲学论证）；经验上思辨，因为非物质的形式难以通过第三人称方法加以验证。",
    "known_empirical_interventions_or_tests": "依赖于驳斥纯物理理论的解释鸿沟（例如关于感受质或自我统一的论证）。（此条目的来源未列出具体的、正面的经验检验。）",
    "criticisms_and_tensions": "面临心理因果问题：解释非物理的形式如何在不违反物理学因果封闭的情况下与物理世界发生因果交互。",
    "open_questions_and_limitations": "支配非物质灵魂／形式及其与物理组成部分之交互的确切结构与定律仍属未知。",
    "ontological_coherence": "内部融贯，因为它主张人是一个单一、统一的实体（避免了笛卡尔式实体二元论的问题），但与物理主义本体论存在根本冲突。"
  },
  "implications": {
    "AI_consciousness": {
      "stance": "否",
      "rationale": "如果意识需要一个特定的、非物理的灵魂／形式／组成部分（它不会由计算自动产生），那么纯粹基于物理机制的人工系统无法达成真正的内在觉知。"
    },
    "survival_beyond_death": {
      "stance": "是",
      "rationale": "非物质的灵魂／形式能够在死亡后独立于物质身体而存续或存在，从而支持死后存续。"
    },
    "meaning_and_purpose": {
      "stance": "是",
      "rationale": "二元论常支持终极的意义／目的／价值，往往与非物质组成部分及可能的神学框架相关。"
    },
    "virtual_immortality": {
      "stance": "否",
      "rationale": "复制物理大脑过程是不够的，因为纯粹数字化的上传缺失所需的非物理组成部分（灵魂／形式）。"
    }
  },
  "relations_and_sources": {
    "related_theories": [
      {
        "name": "Substance Dualism",
        "relationship": "对照（复合二元论强调统一，而非两个不同实体的严格分离）"
      },
      {
        "name": "Stump’s Thomistic Dualism",
        "relationship": "重叠（常被视为这一复合观点的经典哲学框架）"
      },
      {
        "name": "Feser’s Neo-Thomistic Dualism",
        "relationship": "重叠（Feser 主张一种新亚里士多德主义／新托马斯主义的复合结构）"
      },
      {
        "name": "Emergent Dualism",
        "relationship": "兼容（两者都维持不可还原性，但复合二元论往往将非物质的形式视为比从复杂性中涌现更为根本）"
      }
    ],
    "sources_and_references": [
      {
        "title_with_names": "Dualisms (Section 15)",
        "year": ""
      },
      {
        "title_with_names": "Stump’s Thomistic Dualism [Description of the soul as an essentially immaterial/configurational state realized in material components]",
        "year": 1995
      }
    ]
  }
}
