{
  "id_and_class": {
    "theory_title": "अवधान स्कीमा सिद्धांत",
    "summary": "यह सिद्धांत मानता है कि चेतना तब उत्पन्न होती है जब मस्तिष्क अपनी ही अवधान प्रक्रिया का एक त्वरित, सरलीकृत, आंतरिक मॉडल—एक अवधान स्कीमा—निर्मित करता है। मस्तिष्क इस आंतरिक निरूपण की भ्रांतिपूर्वक व्याख्या करता है और इसे एक आत्मनिष्ठ, अभौतिक सार अथवा एक 'स्व-व्यंग्यचित्र' के रूप में प्रस्तुत करता है, यद्यपि यह मूलतः एक अभिकलनात्मक उत्पाद है।",
    "associated_thinkers": [
      "Michael Graziano"
    ],
    "category": "भौतिकवाद",
    "subcategory": "तंत्रिकाजैविक",
    "core_identity_tagline": "चेतना अवधान के विकसित स्व-व्यंग्यचित्र के रूप में",
    "classification_tags": [
      "neuroscience",
      "representation",
      "functionalism",
      "evolution"
    ]
  },
  "conceptual_ground": {
    "explanatory_identity_claim": "चेतना को मस्तिष्क के अपने ही अवधान तंत्र के आंतरिक निरूपण या सरलीकृत मॉडल (अवधान स्कीमा) के रूप में पहचाना जाता है, जो उच्चतर-क्रम विचार का एक विशिष्ट उदाहरण है।",
    "ontological_status": "भौतिकीवाद",
    "mind_body_relationship": "चेतना एक जैविक, सूचना-प्रसंस्करण यंत्र (मस्तिष्क) द्वारा अपने आंतरिक आँकड़ों के आकलन के माध्यम से उत्पन्न विवरण है, अर्थात् मानसिक अवस्थाएँ अभिकलनात्मक और पूर्णतः भौतिक हैं।",
    "primitive_or_emergent_status": "उद्भूत",
    "emergence_type": "दुर्बल उद्भव",
    "subjectivity_and_intentionality": "आत्मनिष्ठता (एक 'प्रेतवत्, अभौतिक सार' का बोध) मस्तिष्क की आंतरिक अवधान स्कीमा द्वारा उत्पन्न भ्रामक विवरण है। आशयिकता का अंतर्निहित रूप से हिसाब रखा जाता है, क्योंकि परिणामी मॉडल का प्राथमिक प्रकार्य संसार में क्रियाओं को नियंत्रित करने हेतु अवधान की निगरानी करना है।",
    "qualia_account": "चेतना को एक 'स्व-व्यंग्यचित्र' अथवा एक अभौतिक सार के भ्रामक विवरण के रूप में वर्णित किया गया है, जो क्वालिया के एक अपस्फीतिकारी या भ्रमवादी विवरण का संकेत देता है, जो डैनियल डेनेट के दृष्टिकोण के समान है।",
    "ontological_commitments": "जैविक मस्तिष्क, सूचना-प्रसंस्करण तंत्र, और आंतरिक निरूपण (अवधान स्कीमा)।",
    "epistemic_access": "चेतना तक स्वयं तंत्र द्वारा अंतर्निरीक्षण के माध्यम से (अपने आंतरिक आँकड़ों का आकलन करते हुए) पहुँचा जाता है, जिससे तंत्र चेतना का दावा करता है, किंतु इसकी वास्तविक अभिकलनात्मक प्रकृति केवल तृतीय-पुरुष वैज्ञानिक विश्लेषण (विज्ञान) द्वारा ही निर्धारित की जा सकती है।",
    "constituents_and_structure": "एक अभिकलनात्मक मॉडल या निरूपण (अवधान स्कीमा) जो मस्तिष्क के अपने ही अवधान तंत्र की निगरानी और नियमन के लिए विकसित किया गया है।"
  },
  "mechanism_and_dynamics": {
    "scope_of_consciousness": "परिघटनात्मक (एक उत्पन्न आंतरिक विवरण/दावे के रूप में), अवधान, क्रिया नियंत्रण।",
    "distinctive_mechanism_or_principle": "अवधान की प्रक्रिया का एक सरलीकृत आंतरिक मॉडल (अवधान स्कीमा) का निर्माण और अनुरक्षण, जो नियंत्रण अभियांत्रिकी के सिद्धांतों में निहित है।",
    "dynamics_of_emergence": "चेतना एक गतिशील, विकसित लक्षण है, जिसका उद्गम एक अभिकलनात्मक रणनीति से होता है जो आंतरिक अवधान स्कीमा उत्पन्न करती है।",
    "location_and_distribution": "मस्तिष्क की जैविक, सूचना-प्रसंस्करण प्रणाली के भीतर स्थित।",
    "causation_and_functional_role": "अवधान स्कीमा की प्रकार्यात्मक भूमिका संसार में क्रियाओं को नियंत्रित करने हेतु मस्तिष्क के अवधान की निगरानी और नियमन करना है। परिणामी क्षमता तंत्र को चेतना का दावा करने में सक्षम बनाती है।",
    "integration_or_binding": "संवेदी आँकड़ों को अवधान स्कीमा में एकीकृत करने का सटीक तंत्र स्रोतों में विस्तृत नहीं है, किंतु सिद्धांत समग्र अवधान की निगरानी और नियमन के लिए आवश्यक एकीकरण को अंतर्निहित करता है।",
    "information_flow_or_representation": "सूचना-प्रसंस्करण केंद्रीय है; मस्तिष्क को अपनी ही अवस्था का एक सरलीकृत निरूपण (अवधान स्कीमा) विकसित करके सूचना की अधिकता को संभालना पड़ता है।",
    "evolutionary_account": "चेतना का लक्षण एक अनुकूली लाभ प्रदान करने के लिए विकसित हुआ: पर्यावरण में क्रियाओं को कुशलता से नियंत्रित करने हेतु अवधान की निगरानी और नियमन।",
    "core_claims_and_evidence": [
      "मस्तिष्क अपनी ही अवधान प्रक्रिया का एक 'त्वरित और अपरिष्कृत मॉडल' (अवधान स्कीमा) विकसित करता है।",
      "मस्तिष्क इस आंतरिक मॉडल को एक 'प्रेतवत्, अभौतिक सार' या एक 'स्व-व्यंग्यचित्र' के रूप में प्रस्तुत करता है।",
      "चेतना का दावा करने की क्षमता नियंत्रण अभियांत्रिकी से प्राप्त अभिकलनों पर आधारित है।"
    ],
    "basis_of_belief_or_evidence_type": "तंत्रिकाजैविक, अभिकलनात्मक, विकासवादी, दार्शनिक।"
  },
  "empirics_and_critiques": {
    "testability_status": "अनुभवजन्य रूप से परीक्षणीय",
    "known_empirical_interventions_or_tests": "",
    "criticisms_and_tensions": "यह सिद्धांत व्याख्या करता है कि कोई तंत्र चेतना का *दावा* कैसे कर सकता है, किंतु इसे समान प्रकार्यवादी मॉडलों की तरह ही सामान्य सीमा का सामना करना पड़ता है—वास्तविक आत्मनिष्ठ अनुभूति ('कोई भीतर है क्या' समस्या) को निर्णायक रूप से सिद्ध या व्याख्यायित करने की, जो प्रस्तावक की अपनी स्वीकृति के अनुसार भी सदैव अनिश्चित रहती है।",
    "open_questions_and_limitations": "अंतर्निरीक्षण पर निर्भर रहने के कारण तंत्र आंतरिक रूप से यह निर्धारित नहीं कर सकता कि उसका चेतना का दावा विशुद्ध रूप से अभिकलनों पर आधारित है। बाह्य प्रेक्षक कभी सचमुच नहीं जान सकता कि तंत्र में कोई आंतरिक अनुभव है या नहीं।",
    "ontological_coherence": "भौतिकवादी ढाँचे के भीतर अत्यधिक संगत, जो चेतना के दावे की व्याख्या करने के लिए अभौतिक द्रव्यों का सहारा लिए बिना अन्य प्रकार्यवादी और अभिकलनात्मक उपागमों के अनुरूप है।"
  },
  "implications": {
    "AI_consciousness": {
      "stance": "संभावित",
      "rationale": "चूँकि चेतना को एक अभिकलनात्मक प्रक्रिया (अवधान स्कीमा का निर्माण) के रूप में परिभाषित किया गया है, अतः सैद्धांतिक रूप से, जो कृत्रिम प्रणालियाँ आवश्यक अभिकलनात्मक वास्तुकला को क्रियान्वित करती हैं वे चेतन बन सकती हैं। इसके अतिरिक्त, प्रेक्षक अनिवार्य रूप से पर्याप्त रूप से जटिल AI प्रणालियों को, जो चेतन होने का व्यवहार करती हैं, चेतना का सामाजिक आरोपण करेंगे।"
    },
    "survival_beyond_death": {
      "stance": "नहीं",
      "rationale": "एक भौतिकवादी/तंत्रिकाजैविक सिद्धांत के रूप में, चेतना भौतिक आधार (जैविक, सूचना-प्रसंस्करण यंत्र) से बँधी है, जो शरीर के क्षय के बाद उत्तरजीविता को असंभव बनाती है।"
    },
    "meaning_and_purpose": {
      "stance": "केवल मानवतावादी",
      "rationale": "चेतना एक अनुकूली, विकासवादी उद्देश्य प्रदान करती है (क्रिया नियंत्रण के लिए अवधान की निगरानी और नियमन), किंतु यह किसी परम या ब्रह्मांडीय अर्थ का संकेत नहीं देती, जो भौतिकवाद के अनुरूप है।"
    },
    "virtual_immortality": {
      "stance": "संभव",
      "rationale": "यदि चेतना एक अभिकलनात्मक संरचना (अवधान स्कीमा) के रूप में साकार होती है, और यदि इस संरचना तथा संबंधित सूचना-प्रसंस्करण प्रणालियों को किसी अजैविक माध्यम पर सटीक रूप से अपलोड किया जा सके, तो आभासी अमरता सैद्धांतिक रूप से संभव है।"
    }
  },
  "relations_and_sources": {
    "related_theories": [
      {
        "name": "Dennett’s Multiple Drafts Model",
        "relationship": "संगत"
      },
      {
        "name": "Bach’s Cortical Conductor Theory",
        "relationship": "संगत"
      },
      {
        "name": "Higher-Order Theories",
        "relationship": "अतिव्यापन"
      },
      {
        "name": "Eliminative Materialism/Illusionism",
        "relationship": "संगत"
      }
    ],
    "sources_and_references": [
      {
        "title_with_names": "True nature of consciousness: solving the biggest mystery of your mind, M. Graziano",
        "year": 2019
      },
      {
        "title_with_names": "Rethinking Consciousness: A Scientific Theory of Subjective Experience, M. Graziano",
        "year": 2019
      },
      {
        "title_with_names": "Can consciousness be non-biological?, M. Graziano",
        "year": 2014
      }
    ]
  }
}
