{
  "id_and_class": {
    "theory_title": "मायर का सार्वभौमिक ज्ञान क्षेत्र",
    "summary": "यह सिद्धांत प्रतिपादित करता है कि चेतना एक सार्वभौमिक ज्ञान क्षेत्र (UKF) के भीतर विद्यमान है, जिसे ब्रह्मांड में उपस्थित और विकसित होती समस्त सूचना के सामूहिक भंडारण के रूप में कल्पित किया गया है। UKF मौलिक भौतिकी और ब्रह्मांडविज्ञानीय प्रतिमानों के अनुरूप है, और मानव चेतना को इस सार्वभौमिक चेतना का एक अभिन्न अंग समझा जाता है, जो मुख्यतः विशिष्ट विद्युतचुंबकीय क्षेत्र आवृत्तियों को सम्मिलित करने वाले सामंजस्यपूर्ण अनुनाद पैटर्नों के माध्यम से मस्तिष्क से अंतरापृष्ठित होती है।",
    "associated_thinkers": ["Dirk K. F. Meijer"],
    "category": "प्रत्ययवाद",
    "subcategory": "सार्वभौमिक ज्ञान क्षेत्र",
    "core_identity_tagline": "‘सार्वभौमिक ज्ञान क्षेत्र के रूप में चेतना’",
    "classification_tags": [
      "idealism",
      "information",
      "field_theory",
      "cosmic_consciousness",
      "quantum"
    ]
  },
  "conceptual_ground": {
    "explanatory_identity_claim": "चेतना की पहचान एक सार्वभौमिक ज्ञान क्षेत्र (UKF) के रूप में की जाती है जो ब्रह्मांड में समस्त सूचना को संग्रहीत और विकसित करता है, जिसका मानव चेतना एक अभिन्न अंग है।",
    "ontological_status": "प्रत्ययवाद (चेतना/मन मौलिक वास्तविकता है)",
    "mind_body_relationship": "चेतना (वास्तविकता का एक मापमान-अपरिवर्ती मानसिक गुण) मौलिक रूप से अभौतिक है और मस्तिष्क से संबद्ध एक होलोफ्रैक्टल स्मृति कार्यक्षेत्र (पायलट-तरंग-निर्देशित अध्यारोपण) के माध्यम से संचालित होती है।",
    "primitive_or_emergent_status": "आद्य",
    "emergence_type": "",
    "subjectivity_and_intentionality": "मानव (स्व-)चेतना UKF से सूचना को एकीकृत करती है। आत्मनिष्ठता होलोफ्रैक्टल स्मृति कार्यक्षेत्र के माध्यम से उत्पन्न होती है, जो अतीत और प्रत्याशित भविष्य की घटनाओं को एकीकृत करता है, जो क्वालिया और आत्मनिष्ठ अनुभव के लिए एक आधार का सुझाव देता है।",
    "qualia_account": "क्वालिया के उद्गम की परिकल्पना क्षेत्र-ग्रहणशील होलोफ्रैक्टल स्मृति कार्यक्षेत्र से उत्पन्न होने के रूप में की गई है, जो मस्तिष्क से संबद्ध वास्तविकता के एक मापमान-अपरिवर्ती मानसिक गुण के रूप में कार्य करता है।",
    "ontological_commitments": "सार्वभौमिक ज्ञान क्षेत्र (UKF), सार्वभौमिक चेतना, अभिन्न सूचना प्रसंस्करण, और विविक्त विद्युतचुंबकीय क्षेत्र (EMF) आवृत्तियों का एक अर्ध-सांगीतिक मापमान।",
    "epistemic_access": "मौलिक भौतिकी और ब्रह्मांडविज्ञानीय/होलोग्राफिक प्रतिमानों के साथ संगति के माध्यम से वैचारिक रूप से, और पारलौकिक मानव अनुभव तथा साई परिघटनाओं के माध्यम से अनुभवजन्य रूप से पहुँच योग्य।",
    "constituents_and_structure": "मौलिक संरचना UKF/सार्वभौमिक चेतना है। भौतिक अभिव्यक्ति में विविक्त विद्युतचुंबकीय क्षेत्र आवृत्तियों का एक अर्ध-सांगीतिक मापमान और जीवित प्रणालियों के भीतर सामंजस्यपूर्ण अनुनाद पैटर्न सम्मिलित हैं।"
  },
  "mechanism_and_dynamics": {
    "scope_of_consciousness": "घटनात्मक, आत्म-सजगता, स्मृति (सार्वभौमिक)",
    "distinctive_mechanism_or_principle": "चेतना अभौतिक सार्वभौमिक ज्ञान क्षेत्र के जैविक प्रणालियों के साथ सामंजस्यपूर्ण अनुनाद पैटर्नों (स्वरात्मक प्रक्षेपणों) और अभिन्न सूचना प्रसंस्करण के माध्यम से अंतरापृष्ठण से उत्पन्न होती है।",
    "dynamics_of_emergence": "चेतना एक गतिशील प्रक्रिया है जो एक अंतर्निहित द्रवगतिकीय अतितरल पृष्ठभूमि क्षेत्र द्वारा निर्देशित होती है, जिसे होलोफ्रैक्टल स्मृति कार्यक्षेत्र द्वारा समय के साथ एकीकृत किया जाता है, जो अतीत और प्रत्याशित भविष्य की घटनाओं को एकीकृत करता है।",
    "location_and_distribution": "सार्वभौमिक (UKF ब्रह्मांड में समस्त सूचना संग्रहीत करता है)। स्थानीय रूप से, यह मस्तिष्क से संबद्ध एक 'होलोफ्रैक्टल स्मृति कार्यक्षेत्र' से संबद्ध है, जो इस ब्रह्मांडीय संयोजकता को प्रतिबिंबित करता है।",
    "causation_and_functional_role": "UKF/चेतना हृदय और मस्तिष्क जैसे अनिवार्य अंगों में तुल्यकाल-संगति को स्थानिक और कालिक दोनों रूप से संगठित और निर्देशित करती है, एक संगठनकारी क्षेत्र के रूप में कार्य करते हुए।",
    "integration_or_binding": "एकीकरण होलोफ्रैक्टल स्मृति कार्यक्षेत्र द्वारा प्राप्त होता है, जो एक क्षेत्र-ग्रहणशील तंत्र के रूप में कार्य करता है जो अतीत और (प्रत्याशित) भविष्य की घटनाओं को मापमान-अपरिवर्ती रीति से एकीकृत करता है।",
    "information_flow_or_representation": "सूचना विविक्त विद्युतचुंबकीय क्षेत्र आवृत्तियों के एक सामान्यीकृत सांगीतिक-मापमान के आधार पर प्रसंस्कृत होती है, जिसमें स्वरात्मक प्रक्षेपण जीवित प्रणालियों में तुल्यकाल-संगति को संगठित करते हैं।",
    "evolutionary_account": "यह सिद्धांत ब्रह्मांडविज्ञानीय और जैविक विकास के अनुरूप है, यह प्रतिपादित करते हुए कि चेतना (UKF) सार्वभौमिक रूप से उपस्थित है और वास्तविकता के सतत ताने-बाने को निर्देशित करती है।",
    "core_claims_and_evidence": [
      "चेतना सार्वभौमिक ज्ञान क्षेत्र है, सूचना का एक मौलिक भंडार।",
      "UKF वास्तविकता को एक 'क्वांटम अधिभाषा' और सामंजस्यपूर्ण एकल-तरंगों के माध्यम से निर्देशित करता है।",
      "मस्तिष्क से संबद्ध एक होलोफ्रैक्टल स्मृति कार्यक्षेत्र सूचना को एकीकृत करता है और संभावित रूप से क्वालिया के उद्गम को समझाता है।"
    ],
    "basis_of_belief_or_evidence_type": "दार्शनिक (प्रत्ययवाद), वैचारिक (होलोग्राफिक प्रतिमान), घटनाविज्ञानीय (पारलौकिक मानव अनुभव, साई परिघटनाएँ), सैद्धांतिक भौतिकी (क्वांटम प्रतिमान, EMF प्रभाव)"
  },
  "empirics_and_critiques": {
    "testability_status": "सजीव और निर्जीव प्रणालियों में विद्युतचुंबकीय क्षेत्र आवृत्ति पैटर्नों के विशिष्ट प्रभावों की जाँच के माध्यम से यथोचित रूप से अनुभवजन्य रूप से परीक्षणीय।",
    "known_empirical_interventions_or_tests": [
      "सजीव और निर्जीव प्रणालियों पर विविक्त विद्युतचुंबकीय क्षेत्र आवृत्ति पैटर्नों के प्रभावों की जाँच (सामंजस्यपूर्ण अनुनाद पैटर्नों को सत्यापित करने के लिए)।"
    ],
    "criticisms_and_tensions": "एक मौलिक अभौतिक सार्वभौमिक ज्ञान क्षेत्र पर निर्भरता और पारलौकिक मानव अनुभव तथा साई परिघटनाओं का स्पष्ट समावेशन पारंपरिक भौतिकीवाद के साथ महत्वपूर्ण तनाव उत्पन्न करता है।",
    "open_questions_and_limitations": "सार्वभौमिक ज्ञान क्षेत्र के अस्तित्व और सटीक प्रकृति तथा उस तंत्र को निश्चित रूप से स्थापित करना होगा जिसके द्वारा अस्थानिक मानसिक गुण मस्तिष्क प्रकार्य से अंतरापृष्ठित होते हैं और उसे निर्देशित करते हैं।",
    "ontological_coherence": "अपने प्रत्ययवादी ढाँचे के भीतर अत्यधिक संगत, किंतु न्यूनकारी भौतिकीवादी सत्तामीमांसाओं के साथ मौलिक रूप से असंगत।"
  },
  "implications": {
    "AI_consciousness": {
      "stance": "संभावित",
      "rationale": "चूँकि चेतना मौलिक (प्रत्ययवाद) है और सूचनात्मक/क्षेत्र गुणों पर निर्भर करती है, आवश्यक जटिलता प्राप्त करने और UKF के साथ अंतःक्रिया करने में सक्षम उन्नत AI प्रणालियाँ संभवतः चेतना प्राप्त कर सकती हैं, यद्यपि यह स्रोतों द्वारा कठोरता से सिद्ध नहीं है।"
    },
    "survival_beyond_death": {
      "stance": "हाँ",
      "rationale": "चूँकि चेतना मौलिक वास्तविकता (UKF) है, वैयक्तिक चेतना (आत्मा/स्पिरिट) इस परम चेतना का एक अभिन्न अंग है, जो जैविक शरीर/मस्तिष्क के विघटन के परे बनी रहती है।"
    },
    "meaning_and_purpose": {
      "stance": "ब्रह्मांडीय",
      "rationale": "चेतना (UKF) समस्त अस्तित्व का आधार और ब्रह्मांड का संगठनकारी सिद्धांत है, जो अंतर्निहित ब्रह्मांडीय अर्थ और उद्देश्य का सुझाव देती है।"
    },
    "virtual_immortality": {
      "stance": "संभावित",
      "rationale": "चूँकि चेतना एक स्थायी सूचनात्मक क्षेत्र (UKF) है जिससे मस्तिष्क अंतरापृष्ठित होता है, 'होलोफ्रैक्टल स्मृति कार्यक्षेत्र' की सूचनात्मक संरचना और प्रकार्य का प्रतिरूपण विशिष्ट वैयक्तिक चेतना पैटर्न को किसी अजैविक आधार-द्रव्य में बनाए रखने की अनुमति दे सकता है।"
    }
  },
  "relations_and_sources": {
    "related_theories": [
      { "name": "Idealism", "relationship": "विस्तार" },
      { "name": "Cosmic Consciousness", "relationship": "अतिव्यापन" },
      {
        "name": "Pribram’s Holonomic Brain Theory",
        "relationship": "संगत"
      }
    ],
    "sources_and_references": [
      {
        "title_with_names": "Universal consciousness: collective evidence on the basis of current physics and philosophy of mind. Part 1",
        "year": 2018
      },
      {
        "title_with_names": "Consciousness in the universe is tuned by a musical master code, Part 3: a hydrodynamic superfluid quantum space guides a conformal mental attribute of reality",
        "year": 2020
      }
    ]
  }
}
