{
  "id_and_class": {
    "theory_title": "वैन इनवेगन का ईसाई भौतिकवाद और मृतकों का पुनरुत्थान",
    "summary": "यह सिद्धांत ईसाई भौतिकवाद का एक रूप प्रस्तावित करता है जहाँ मानव व्यक्ति पूर्णतः एक भौतिक सत्ता है, इस प्रकार दार्शनिक और बाइबिलीय दोनों आधारों पर द्रव्य द्वैतवाद को अस्वीकार करता है। यह तर्क देता है कि मृत्यु के आर-पार वैयक्तिक पहचान ईश्वर द्वारा अंतिम पुनरुत्थान तक मूल भौतिक शरीर के एक भौतिक और कारणात्मक रूप से सतत 'नग्न बीज' को संरक्षित करने के द्वारा बनी रहती है।",
    "associated_thinkers": ["Peter van Inwagen"],
    "category": "गैर-न्यूनकारी भौतिकीवाद",
    "subcategory": "ईसाई भौतिकवाद",
    "core_identity_tagline": "बाइबिलीय पुनरुत्थान के साथ समाधानित भौतिकवाद",
    "classification_tags": [
      "christian philosophy",
      "materialism",
      "personal identity",
      "theology",
      "resurrection"
    ]
  },
  "conceptual_ground": {
    "explanatory_identity_claim": "सचेत व्यक्ति एक भौतिक वस्तु है जिसे वैयक्तिक पहचान बनाए रखने के लिए भौतिक और कारणात्मक सातत्य बनाए रखना आवश्यक है।",
    "ontological_status": "ईसाई भौतिकवाद (एक अद्वितीय भौतिकीवादी अवस्थिति जो पहचान सातत्य के लिए दिव्य क्रिया को समाविष्ट करती है)।",
    "mind_body_relationship": "तादात्म्य सिद्धांत: व्यक्ति (मन सहित) एक भौतिक वस्तु के तादात्म्य है, यद्यपि दीर्घकालिक अस्तित्व के लिए सटीक तंत्र दिव्य संरक्षण पर निर्भर करता है।",
    "primitive_or_emergent_status": "उद्भूत",
    "emergence_type": "यह सिद्धांत विशिष्ट तंत्रिकावैज्ञानिक उद्भव तंत्रों के बजाय सत्तामीमांसीय सातत्य (भौतिक सत्ता का ईश्वर द्वारा संरक्षण) पर केंद्रित है, किंतु जीवनकाल के दौरान चेतना का एक भौतिकीवादी/भौतिकवादी विवरण मान लेता है।",
    "subjectivity_and_intentionality": "आत्मनिष्ठता और आशयिकता भौतिक व्यक्ति/मस्तिष्क के गुण हैं, जो मानक भौतिकवादी अवस्थितियों के अनुरूप हैं, क्योंकि यह सिद्धांत मुख्यतः जीवनकाल के दौरान सचेत प्रकार्य के बजाय मृत्युपरांत सातत्य पर केंद्रित है।",
    "qualia_account": "यह सिद्धांत मुख्यतः सत्तामीमांसीय सातत्य से सरोकार रखता है, किंतु अंतर्निहित रूप से मान लेता है कि गुणात्मक अनुभव भौतिक जीव की एक पूर्णतः भौतिक परिघटना है, जो इसके अंतर्निहित भौतिकवादी आधार के अनुरूप है।",
    "ontological_commitments": "भौतिक व्यक्ति/शरीर, परमाणु, और ईश्वर की शक्ति (भौतिक तथा कारणात्मक सातत्य को सुरक्षित करने के लिए)। यह आत्मा जैसे अभौतिक द्रव्यों को अस्वीकार करता है।",
    "epistemic_access": "दार्शनिक तर्कणा और धार्मिक व्याख्याशास्त्र के माध्यम से पहुँच प्राप्य, विशेषकर मृत्यु और पुनरुत्थान संबंधी बाइबिलीय ग्रंथों पर केंद्रित।",
    "constituents_and_structure": "मूल घटक भौतिक शरीर है, विशेष रूप से वह भाग जो मृत्यु के पश्चात पहचान सातत्य बनाए रखता है, जिसका प्रतीक 'गुम्नोस कोक्कोस' (नग्न बीज या अनावृत दाना) है।"
  },
  "mechanism_and_dynamics": {
    "scope_of_consciousness": "वैयक्तिक पहचान, मृत्यु के परे अस्तित्व, धार्मिक संगति।",
    "distinctive_mechanism_or_principle": "वह तंत्र जिसके द्वारा ईश्वर मृत्यु और पुनरुत्थान के बीच व्यक्ति के भौतिक और कारणात्मक सातत्य को सुनिश्चित करने के लिए मूल पदार्थ के एक छोटे अंश (एक नग्न बीज) को संरक्षित करता है।",
    "dynamics_of_emergence": "चेतना जीवनकाल के दौरान जटिल भौतिक जीव से उत्पन्न होती है। मृत्यु के आर-पार इसकी निरंतरता सतत नहीं है बल्कि ईश्वर द्वारा भौतिक आधारद्रव्य के एक तत्व को धारित करके सुरक्षित की जाती है।",
    "location_and_distribution": "जीवनकाल के दौरान भौतिक शरीर/मस्तिष्क में अवस्थित। पहचान सातत्य मृत्यु के पश्चात एक 'गुम्नोस कोक्कोस' के संरक्षण द्वारा बनाए रखा जाता है।",
    "causation_and_functional_role": "व्यक्ति की चेतना और मानसिक जीवन भौतिक क्षेत्र के भीतर कारणात्मक रूप से प्रभावकारी हैं, क्योंकि वे भौतिक सत्ता के गुण हैं।",
    "integration_or_binding": "जीवनकाल के दौरान चेतना की संगति को भौतिक शरीर के भीतर तंत्रिका प्रक्रियाओं के माध्यम से प्राप्त माना जाता है, जो एक भौतिकवादी ढाँचे के अनुरूप है।",
    "information_flow_or_representation": "सचेत संसाधन भौतिक मस्तिष्क के भीतर प्रकार्यात्मक निरूपण और सूचना प्रवाह पर आधारित है।",
    "evolutionary_account": "जीवनकाल के दौरान चेतना का उद्भव जैविक और विकासात्मक प्रक्रियाओं का अनुसरण करता है, जैसा कि इसकी भौतिकवादी अवस्थिति द्वारा समर्थित है।",
    "core_claims_and_evidence": [
      "मानव व्यक्ति एक भौतिक वस्तु है, जो द्रव्य द्वैतवाद को अस्वीकार करता है।",
      "नए नियम के पुनरुत्थान ग्रंथों की पारंपरिक द्वैतवादी समझ जटिल है, जो एक भौतिकवादी पठन के पक्ष में है।",
      "ईश्वर को पुनरुत्थान के लिए भौतिक और कारणात्मक सातत्य सुनिश्चित करने हेतु व्यक्ति के किसी भौतिक 'गुम्नोस कोक्कोस' को संरक्षित करना होगा।"
    ],
    "basis_of_belief_or_evidence_type": "दार्शनिक तर्क, धार्मिक/बाइबिलीय व्याख्याशास्त्र।"
  },
  "empirics_and_critiques": {
    "testability_status": "अनुमानात्मक/संकल्पनात्मक। पुनरुत्थान संबंधी केंद्रीय दावे दार्शनिक/धार्मिक तर्क पर निर्भर करते हैं और विज्ञान द्वारा अनुभवजन्य रूप से परीक्षणीय नहीं हैं।",
    "known_empirical_interventions_or_tests": "",
    "criticisms_and_tensions": "इस सिद्धांत को यह समझाने में कठिनाई का सामना करना पड़ता है कि सर्वशक्तिमत्ता ऐसे व्यक्ति को कैसे पुनःसंयोजित कर सकती है जिसके परमाणु प्रवाहित होकर व्यापक रूप से फैल गए हैं (असंख्य प्रतिलिपियों की पहेली)। इसके अतिरिक्त, अमर आत्मा के विरुद्ध तर्क अनेक ईसाई द्वैतवादियों को समझाने में विफल रहा।",
    "open_questions_and_limitations": "वह सटीक तंत्र जिसके द्वारा ईश्वर 'गुम्नोस कोक्कोस' को संरक्षित करता है और शारीरिक परमाणुओं के निरंतर प्रवाह तथा प्रकीर्णन को देखते हुए वैयक्तिक पहचान सुनिश्चित करता है, एक अनसुलझी अपेक्षा बना रहता है।",
    "ontological_coherence": "भौतिकवाद को ईसाई सिद्धांत के साथ समाधानित करने में संगत, किंतु एक ऐसे तंत्र (दिव्य संरक्षण) पर निर्भर करता है जो भौतिक सातत्य को सुरक्षित करने के लिए एक अलौकिक तत्व प्रस्तुत करता है।"
  },
  "implications": {
    "AI_consciousness": {
      "stance": "संभावित",
      "rationale": "एक भौतिकवादी सिद्धांत के रूप में, चेतना अंततः जटिल भौतिक व्यवस्था का उत्पाद है, जिसका अर्थ है कि यदि आवश्यक भौतिक आधारद्रव्य प्राप्त हो जाए तो AI सैद्धांतिक रूप से चेतना को साकार करने में सक्षम होना चाहिए।"
    },
    "survival_beyond_death": {
      "stance": "हाँ (दिव्य हस्तक्षेप पर सशर्त)",
      "rationale": "सिद्धांत का प्राथमिक लक्ष्य भौतिक व्यक्ति के लिए बाइबिलीय पुनरुत्थान और मृत्युपरांत अस्तित्व प्राप्त करने हेतु एक तंत्र (ईश्वर द्वारा एक नग्न बीज को संरक्षित करना) प्रदान करना है।"
    },
    "meaning_and_purpose": {
      "stance": "ब्रह्मांडीय/धार्मिक",
      "rationale": "संपूर्ण ढाँचा मृतकों के पुनरुत्थान के प्रति एक धार्मिक प्रतिबद्धता द्वारा अवलंबित है, जो एक दिव्य योजना के भीतर परम अर्थ और उद्देश्य को निहित करता है।"
    },
    "virtual_immortality": {
      "stance": "संभावित",
      "rationale": "चूँकि व्यक्ति एक भौतिक वस्तु है, मस्तिष्क की संपूर्ण भौतिक अवस्था को अपलोड करना सैद्धांतिक रूप से सचेत स्व की एक प्रकार्यात्मक प्रतिलिपि में परिणत होना चाहिए, जो आभासी अमरता की अनुमति देता है।"
    }
  },
  "relations_and_sources": {
    "related_theories": [
      { "name": "Substance Dualism", "relationship": "आलोचना" },
      { "name": "Papineau’s Mind-Brain Identity", "relationship": "अतिव्यापन" },
      {
        "name": "Murphy’s Non-Reductive Physicalism",
        "relationship": "संगत"
      },
      { "name": "Mind-Brain Identity Theory", "relationship": "अतिव्यापन" }
    ],
    "sources_and_references": [
      {
        "title_with_names": "Dualism and Materialism: Athens and Jerusalem?",
        "year": 1995
      },
      {
        "title_with_names": "A materialist ontology of the human person",
        "year": 2007
      },
      {
        "title_with_names": "What is the nature of personal identity?",
        "year": 2007
      }
    ]
  }
}
